_version.py
cad_to_dagmc/__init__.py
cad_to_dagmc/core.py
cad_to_dagmc/direct_mesh_plugin.py
cad_to_dagmc-0.9.7.dist-info/licenses/LICENSE
cad_to_dagmc-0.9.7.dist-info/METADATA
cad_to_dagmc-0.9.7.dist-info/WHEEL
cad_to_dagmc-0.9.7.dist-info/top_level.txt
cad_to_dagmc-0.9.7.dist-info/RECORD
