Metadata-Version: 2.4
Name: cad_to_dagmc
Version: 0.9.7
Summary: Converts CAD files to a DAGMC h5m file
Author-email: Jonathan Shimwell <mail@jshimwell.com>
Project-URL: Homepage, https://github.com/fusion-energy/cad_to_dagmc
Project-URL: Bug Tracker, https://github.com/fusion-energy/cad_to_dagmc/issues
Keywords: dagmc,geometry,plot,slice
Classifier: Programming Language :: Python :: 3
Classifier: License :: OSI Approved :: MIT License
Classifier: Operating System :: OS Independent
Requires-Python: >=3.8
License-File: LICENSE
Requires-Dist: trimesh
Requires-Dist: networkx
Requires-Dist: cadquery>=2.5.2
Requires-Dist: numpy
Requires-Dist: gmsh
Provides-Extra: tests
Requires-Dist: pytest; extra == "tests"
Requires-Dist: vtk; extra == "tests"
Requires-Dist: assembly-mesh-plugin; extra == "tests"
Dynamic: license-file
